Metadata-Version: 1.0
Name: remember-forever
Version: 0.2
Summary: weixiao & yandong love story
Home-page: UNKNOWN
Author: UNKNOWN
Author-email: UNKNOWN
License: UNKNOWN
Platform: UNKNOWN
